hunana/__init__.py
hunana/dynamic_constants.py
hunana/entropy.py
hunana/hunana.py
hunana/bin/__init__.py
hunana/bin/_hunana.py
hunana/core/__init__.py
hunana/core/header_decode.py
hunana/datatypes/__init__.py
hunana/datatypes/motif_classes.py
hunana/datatypes/position.py
hunana/datatypes/variant.py
hunana/datatypes/variant_counter.py
hunana/datatypes/variant_dictionary.py
hunana/errorhandlers/__init__.py
hunana/errorhandlers/exceptions.py
HUNANA-1.0.7.dist-info/METADATA
HUNANA-1.0.7.dist-info/WHEEL
HUNANA-1.0.7.dist-info/entry_points.txt
HUNANA-1.0.7.dist-info/top_level.txt
HUNANA-1.0.7.dist-info/RECORD
