Metadata-Version: 2.1
Name: HUNANA
Version: 1.0.7
Summary: HUNANA
Home-page: https://github.com/pu-sds/hunana
Author: Perdana University - School of Data Sciences
Author-email: pu.sds@perdanauniversity.edu.my
License: UNKNOWN
Platform: UNKNOWN
Classifier: Programming Language :: Python :: 3
Classifier: License :: OSI Approved :: MIT License
Classifier: Operating System :: OS Independent
Requires-Python: >=3.6
Requires-Dist: biopython (>=1.6)
Requires-Dist: scipy (>=1.5)
Requires-Dist: jsonpickle (>=1.5)
